gcodepy/__init__.py
gcodepy/gcode.py
gcodepy/util.py
gcodepy-0.1.1.dist-info/LICENSE
gcodepy-0.1.1.dist-info/METADATA
gcodepy-0.1.1.dist-info/WHEEL
gcodepy-0.1.1.dist-info/top_level.txt
gcodepy-0.1.1.dist-info/RECORD
