Metadata-Version: 2.1
Name: gcodepy
Version: 0.1.1
Summary: Tool to generate g-code for Marlin based printers
Home-page: https://github.com/rmeno12/gcodepy
Author: Rahul Menon
Author-email: menonrahul02@gmail.com
License: UNKNOWN
Platform: UNKNOWN
Classifier: Programming Language :: Python :: 3
Classifier: License :: OSI Approved :: MIT License
Classifier: Operating System :: OS Independent
Requires-Python: >=3.8
License-File: LICENSE
